postoffice_django/__init__.py
postoffice_django/admin.py
postoffice_django/apps.py
postoffice_django/checks.py
postoffice_django/config.py
postoffice_django/exceptions.py
postoffice_django/models.py
postoffice_django/publishing.py
postoffice_django/serializers.py
postoffice_django/settings.py
postoffice_django/urls.py
postoffice_django/api/__init__.py
postoffice_django/api/views.py
postoffice_django/management/__init__.py
postoffice_django/management/commands/__init__.py
postoffice_django/management/commands/configure_postoffice.py
postoffice_django/management/commands/configure_postoffice_publishers.py
postoffice_django/management/commands/configure_postoffice_topics.py
postoffice_django/migrations/0001_initial.py
postoffice_django/migrations/0002_add_bulk_field.py
postoffice_django/migrations/0003_set_json_encoder.py
postoffice_django/migrations/0004_alter_id_to_bigautofield.py
postoffice_django/migrations/__init__.py
tests/api/__init__.py
tests/api/test_views.py
postoffice_django-0.12.1.dist-info/LICENSE
postoffice_django-0.12.1.dist-info/METADATA
postoffice_django-0.12.1.dist-info/WHEEL
postoffice_django-0.12.1.dist-info/top_level.txt
postoffice_django-0.12.1.dist-info/RECORD
