Metadata-Version: 2.1
Name: postoffice_django
Version: 0.12.1
Summary: A simple Django app to comunicate with postoffice
Home-page: https://github.com/mercadona/postoffice_django/
Author: Mercadona
Author-email: sofware.online@mercadona.es
License: APACHE License
Platform: UNKNOWN
Classifier: Environment :: Web Environment
Classifier: Framework :: Django :: 2.0
Classifier: Framework :: Django :: 2.1
Classifier: Framework :: Django :: 2.2
Classifier: Framework :: Django :: 3.0
Classifier: Intended Audience :: Developers
Classifier: License :: OSI Approved :: Apache Software License
Classifier: Natural Language :: English
Classifier: Programming Language :: Python :: 3
Classifier: Programming Language :: Python :: 3.7
Classifier: Programming Language :: Python :: 3.8
License-File: LICENSE
